{
	"result":0,
	"data":[
		{
			"title": "主页",
			"url": "home",
			"submenus": []
		},
		{
			"title": "课程",
			"url": "courses",
			"submenus": [
				{
					"title": "Vue",
					"url": "vue"
				},
				{
					"title": "NodeJS",
					"url": "nodejs"
				},
				{
					"title": "Webpack",
					"url": "webpack"
				}
			]
		},
		{
			"title": "路径",
			"url": "path",
			"submenus": []
		},
		{
			"title": "实战",
			"url": "list",
			"submenus": []
		},
		{
			"title": "笔记",
			"url": "notebook",
			"submenus": []
		},
		{
			"title": "博客",
			"url": "blog",
			"submenus": []
		},
		{
			"title": "交流",
			"url": "commit",
			"submenus": [
				{
					"title": "Git",
					"url": "git"
				},
				{

					"title": "Weixin",
					"url": "weixin"
				}
			]
		}
	],
	"msg":"",
	"code": 0
}